ssvad_metrics/VERSION
ssvad_metrics/__init__.py
ssvad_metrics/_utils.py
ssvad_metrics/criteria.py
ssvad_metrics/data_schema.py
ssvad_metrics/metrics.py
ssvad_metrics/utils.py
ssvad_metrics/visualizer.py
py_ssvad_metrics-1.0.0.dist-info/LICENSE
py_ssvad_metrics-1.0.0.dist-info/METADATA
py_ssvad_metrics-1.0.0.dist-info/WHEEL
py_ssvad_metrics-1.0.0.dist-info/entry_points.txt
py_ssvad_metrics-1.0.0.dist-info/top_level.txt
py_ssvad_metrics-1.0.0.dist-info/RECORD
