Metadata-Version: 2.1
Name: py-ssvad-metrics
Version: 1.0.0
Summary: Single Scene Video Anomaly Detection Metrics
Home-page: https://github.com/qlue-dev/py-ssvad-metrics
Author: PT Qlue Performa Indonesia
Author-email: developer@qlue.id
License: UNKNOWN
Platform: UNKNOWN
Classifier: License :: OSI Approved :: GNU General Public License v3 (GPLv3)
Classifier: Intended Audience :: Developers
Classifier: Intended Audience :: Science/Research
Classifier: Topic :: Scientific/Engineering :: Artificial Intelligence
Classifier: Development Status :: 4 - Beta
Requires-Python: >=3.6,<4
License-File: LICENSE
Requires-Dist: numpy (>=1.18)
Requires-Dist: typing-extensions (>=3.7.4)
Requires-Dist: pytest (>=6.2.3)
Requires-Dist: scikit-learn (>=0.24.1)
Requires-Dist: scipy (>=1.5.4)
Requires-Dist: pydantic (>=1.8.1)
Requires-Dist: pandas (>=1.1.5)
Requires-Dist: tqdm (>=4.58.0)
Requires-Dist: numba (>=0.53.1)
Requires-Dist: ffmpeg-python (>=0.2.0)
